tests/__init__.py
tests/conftest.py
tests/test_shell_motorsport.py
shell_motorsport-0.1.1.dist-info/METADATA
shell_motorsport-0.1.1.dist-info/WHEEL
shell_motorsport-0.1.1.dist-info/top_level.txt
shell_motorsport-0.1.1.dist-info/RECORD
